telekinesis/__init__.py
telekinesis/broker.py
telekinesis/client.py
telekinesis/cryptography.py
telekinesis/fake_websockets.py
telekinesis/helpers.py
telekinesis/telekinesis.py
telekinesis-0.1.89.dist-info/licenses/LICENSE
telekinesis-0.1.89.dist-info/METADATA
telekinesis-0.1.89.dist-info/WHEEL
telekinesis-0.1.89.dist-info/top_level.txt
telekinesis-0.1.89.dist-info/RECORD
